[
    {
        "name":"Sue Herrera",
        "about": {
            "title":"",
            "description": "My name is Sue Herrera and into my veins there are variables and musical notes; I'm a cellist and recently I started creating with a new ingredient: Code. I am training as a front-end, but in my sAboutTextare time I disguise myself as a teacher and crossfitter.",
        },
        "works": {
            "title":"Works related with code",
            "charge":["Front-end Jr.","Operation developer"]  
        },
        "studies": {
            "title":"Studies",
            "charge":["Violoncello","Music Education","Front-end training"]   
        },
        "skills": {
            "title":"skills",
            "subtitles": {
                "tech": "skills with the PC",
                "soft": "skills with my heart"
            },
            "techSkills": ["Javascript","HTML","CSS","react","vue","hyperscript","wordpress","Jquery"],
            "softSkills": ["Empathic","Positive","Musician","good at listening","love excercing","teaching skills"]
        }
    }
]